napari_pyav/__init__.py
napari_pyav/_reader.py
napari_pyav/napari.yaml
napari_pyav/_tests/__init__.py
napari_pyav/_tests/test_reader.py
napari_pyav-0.0.10.dist-info/licenses/LICENSE
napari_pyav-0.0.10.dist-info/METADATA
napari_pyav-0.0.10.dist-info/WHEEL
napari_pyav-0.0.10.dist-info/entry_points.txt
napari_pyav-0.0.10.dist-info/top_level.txt
napari_pyav-0.0.10.dist-info/RECORD
