Metadata-Version: 2.4
Name: napari-pyav
Version: 0.0.10
Summary: Napari plugin for reading videos using PyAV
Author: jlab.berlin
Author-email: yourname@example.com
License: 
Project-URL: Homepage, https://github.com/danionella/napari-pyav
Project-URL: Bug Tracker, https://github.com/danionella/napari-pyav/issues
Project-URL: Documentation, https://github.com/danionella/napari-pyav#README.md
Project-URL: Source Code, https://github.com/danionella/napari-pyav
Project-URL: User Support, https://github.com/danionella/napari-pyav/issues
Classifier: Development Status :: 2 - Pre-Alpha
Classifier: Framework :: napari
Classifier: Intended Audience :: Developers
Classifier: License :: OSI Approved :: MIT License
Classifier: Operating System :: OS Independent
Classifier: Programming Language :: Python
Classifier: Programming Language :: Python :: 3
Classifier: Programming Language :: Python :: 3 :: Only
Classifier: Programming Language :: Python :: 3.9
Classifier: Programming Language :: Python :: 3.10
Classifier: Programming Language :: Python :: 3.11
Classifier: Programming Language :: Python :: 3.12
Classifier: Topic :: Scientific/Engineering :: Image Processing
Requires-Python: >=3.9
License-File: LICENSE
Requires-Dist: numpy
Requires-Dist: av<14
Provides-Extra: testing
Requires-Dist: tox; extra == "testing"
Requires-Dist: pytest; extra == "testing"
Requires-Dist: pytest-cov; extra == "testing"
Dynamic: license-file
